{
  "schema": "tinynpu.qllama_quant_config.v1",
  "model": {
    "vocab_size": 128,
    "max_seq_len": 16,
    "n_layers": 2,
    "d_model": 32,
    "d_head": 16,
    "n_heads": 2,
    "n_kv_heads": 1,
    "ffn_hidden_dim": 32
  },
  "quantization": {
    "activation_qmax": 32767,
    "weight_qmax": 32767,
    "attn_scale": 0.00390625,
    "multiplier_bits": 16,
    "precision_policy": "int16_baseline",
    "activation_bits": 16,
    "weight_bits": 16,
    "score_out_bits": 16,
    "prob_bits": 16,
    "value_cache_bits": 16
  },
  "global_activation_scales": {
    "embedding_out": 0.0003183494919954006,
    "final_norm": 0.00022198942580541517,
    "lm_head_logits": 0.001291805943091002
  },
  "weight_scales": {
    "tok_embeddings.weight": 0.00012082107248939884,
    "layers.0.attn.q_proj.weight": 1.608150851633033e-05,
    "layers.0.attn.k_proj.weight": 2.2244852892439422e-05,
    "layers.0.attn.v_proj.weight": 1.2816201924921178e-05,
    "layers.0.attn.o_proj.weight": 1.686496752373019e-05,
    "layers.0.mlp.gate_proj.weight": 1.911921893636799e-05,
    "layers.0.mlp.up_proj.weight": 2.0096840979098533e-05,
    "layers.0.mlp.down_proj.weight": 1.9415930628860225e-05,
    "layers.1.attn.q_proj.weight": 2.1131171747097567e-05,
    "layers.1.attn.k_proj.weight": 1.96803633693111e-05,
    "layers.1.attn.v_proj.weight": 9.803568858100886e-06,
    "layers.1.attn.o_proj.weight": 9.353510769634414e-06,
    "layers.1.mlp.gate_proj.weight": 1.6970166529334927e-05,
    "layers.1.mlp.up_proj.weight": 1.3239929338222886e-05,
    "layers.1.mlp.down_proj.weight": 1.3245388292016976e-05,
    "lm_head.weight": 0.00012082107248939884
  },
  "lm_head": {
    "input_scale": 0.00022198942580541517,
    "rhs_scale": 0.00012082107248939884,
    "output_scale": 0.001291805943091002,
    "in_bits": 16,
    "rhs_bits": 16,
    "out_bits": 16,
    "real_multiplier": 2.076240680774347e-05,
    "multiplier": 44587,
    "shift": 31,
    "approx": 2.076243981719017e-05,
    "relative_error": 1.5898660982274598e-06
  },
  "layers": {
    "0": {
      "activation_scales": {
        "attn_cat": 0.00031738807511495564,
        "attn_probs": 0.00012199712926077327,
        "down_out": 0.0014032200424535241,
        "ffn_hidden": 0.0022028791585723614,
        "gate_out": 0.0006305648357552961,
        "k_out": 0.0005318924935654892,
        "o_out": 0.0003075407852752205,
        "q_out": 0.0005835991408737307,
        "resid1": 0.00041640190512920645,
        "resid2": 0.0015019858193447005,
        "rms1_out": 0.0003433445262291859,
        "rms2_out": 0.00037603421374826174,
        "rope_k": 0.000536329564907338,
        "rope_q": 0.000545260525203831,
        "score_logits": 0.001277046287442546,
        "silu_gate": 0.0006269827064846683,
        "up_out": 0.0005585197534422606,
        "v_out": 0.0003196729756204975
      },
      "score_scale": 7.310983506092934e-08,
      "matmuls": {
        "q_proj": {
          "input_scale": 0.0003433445262291859,
          "rhs_scale": 1.608150851633033e-05,
          "output_scale": 0.0005835991408737307,
          "in_bits": 16,
          "rhs_bits": 16,
          "out_bits": 16,
          "real_multiplier": 9.46111386374488e-06,
          "multiplier": 40635,
          "shift": 32,
          "approx": 9.461073204874992e-06,
          "relative_error": 4.297471785445239e-06
        },
        "k_proj": {
          "input_scale": 0.0003433445262291859,
          "rhs_scale": 2.2244852892439422e-05,
          "output_scale": 0.0005318924935654892,
          "in_bits": 16,
          "rhs_bits": 16,
          "out_bits": 16,
          "real_multiplier": 1.4359383841261456e-05,
          "multiplier": 61673,
          "shift": 32,
          "approx": 1.4359364286065102e-05,
          "relative_error": 1.3618409098196735e-06
        },
        "v_proj": {
          "input_scale": 0.0003433445262291859,
          "rhs_scale": 1.2816201924921178e-05,
          "output_scale": 0.0003196729756204975,
          "in_bits": 16,
          "rhs_bits": 16,
          "out_bits": 16,
          "real_multiplier": 1.3765232326656173e-05,
          "multiplier": 59121,
          "shift": 32,
          "approx": 1.3765180483460426e-05,
          "relative_error": 3.7662419722843424e-06
        },
        "score": {
          "input_scale": 0.000545260525203831,
          "rhs_scale": 0.0001340823912268345,
          "output_scale": 3.897354922460238e-08,
          "in_bits": 16,
          "rhs_bits": 16,
          "out_bits": 16,
          "real_multiplier": 1.8758834264644837,
          "multiplier": 61469,
          "shift": 15,
          "approx": 1.875885009765625,
          "relative_error": 8.440296017167027e-07
        },
        "value": {
          "input_scale": 0.00390625,
          "rhs_scale": 0.0003196729756204975,
          "output_scale": 0.00031738807511495564,
          "in_bits": 16,
          "rhs_bits": 16,
          "out_bits": 16,
          "real_multiplier": 0.003934371386087174,
          "multiplier": 8251,
          "shift": 21,
          "approx": 0.003934383392333984,
          "relative_error": 3.051630268706385e-06
        },
        "o_proj": {
          "input_scale": 0.00031738807511495564,
          "rhs_scale": 1.686496752373019e-05,
          "output_scale": 0.0003075407852752205,
          "in_bits": 16,
          "rhs_bits": 16,
          "out_bits": 16,
          "real_multiplier": 1.7404974674961435e-05,
          "multiplier": 37377,
          "shift": 31,
          "approx": 1.740502193570137e-05,
          "relative_error": 2.7153581557833744e-06
        },
        "gate_proj": {
          "input_scale": 0.00037603421374826174,
          "rhs_scale": 1.911921893636799e-05,
          "output_scale": 0.0006305648357552961,
          "in_bits": 16,
          "rhs_bits": 16,
          "out_bits": 16,
          "real_multiplier": 1.140165142828872e-05,
          "multiplier": 24485,
          "shift": 31,
          "approx": 1.1401716619729996e-05,
          "relative_error": 5.71771919929595e-06
        },
        "up_proj": {
          "input_scale": 0.00037603421374826174,
          "rhs_scale": 2.0096840979098533e-05,
          "output_scale": 0.0005585197534422606,
          "in_bits": 16,
          "rhs_bits": 16,
          "out_bits": 16,
          "real_multiplier": 1.3530586429259412e-05,
          "multiplier": 58113,
          "shift": 32,
          "approx": 1.3530487194657326e-05,
          "relative_error": 7.334094690193483e-06
        },
        "down_proj": {
          "input_scale": 0.0022028791585723614,
          "rhs_scale": 1.9415930628860225e-05,
          "output_scale": 0.0014032200424535241,
          "in_bits": 16,
          "rhs_bits": 16,
          "out_bits": 16,
          "real_multiplier": 3.04805715658238e-05,
          "multiplier": 65457,
          "shift": 31,
          "approx": 3.048079088330269e-05,
          "relative_error": 7.1953204162967325e-06
        }
      }
    },
    "1": {
      "activation_scales": {
        "attn_cat": 0.000344358656581338,
        "attn_probs": 0.00011887959021669709,
        "down_out": 0.001236832224832264,
        "ffn_hidden": 0.001123836546674227,
        "gate_out": 0.00044027371453709136,
        "k_out": 0.0005849294065192074,
        "o_out": 0.000672473646668546,
        "q_out": 0.0007198196004095161,
        "resid1": 0.0018445132431013508,
        "resid2": 0.0026007472864802306,
        "rms1_out": 0.0003421356674807221,
        "rms2_out": 0.0003201958315521788,
        "rope_k": 0.0005619953496888973,
        "rope_q": 0.0006898622229893614,
        "score_logits": 0.0013412593878344467,
        "silu_gate": 0.0004284934324595885,
        "up_out": 0.0005301359211797461,
        "v_out": 0.00037490851479475497
      },
      "score_scale": 9.692484031151655e-08,
      "matmuls": {
        "q_proj": {
          "input_scale": 0.0003421356674807221,
          "rhs_scale": 2.1131171747097567e-05,
          "output_scale": 0.0007198196004095161,
          "in_bits": 16,
          "rhs_bits": 16,
          "out_bits": 16,
          "real_multiplier": 1.0043804789741627e-05,
          "multiplier": 21569,
          "shift": 31,
          "approx": 1.0043848305940628e-05,
          "relative_error": 4.3326408579149024e-06
        },
        "k_proj": {
          "input_scale": 0.0003421356674807221,
          "rhs_scale": 1.96803633693111e-05,
          "output_scale": 0.0005849294065192074,
          "in_bits": 16,
          "rhs_bits": 16,
          "out_bits": 16,
          "real_multiplier": 1.1511396388311521e-05,
          "multiplier": 49441,
          "shift": 32,
          "approx": 1.1511379852890968e-05,
          "relative_error": 1.4364391595328782e-06
        },
        "v_proj": {
          "input_scale": 0.0003421356674807221,
          "rhs_scale": 9.803568858100886e-06,
          "output_scale": 0.00037490851479475497,
          "in_bits": 16,
          "rhs_bits": 16,
          "out_bits": 16,
          "real_multiplier": 8.94658414679061e-06,
          "multiplier": 38425,
          "shift": 32,
          "approx": 8.94651748239994e-06,
          "relative_error": 7.451379160488774e-06
        },
        "score": {
          "input_scale": 0.0006898622229893614,
          "rhs_scale": 0.00014049883742222433,
          "output_scale": 4.0933237337395755e-08,
          "in_bits": 16,
          "rhs_bits": 16,
          "out_bits": 16,
          "real_multiplier": 2.3678762447398225,
          "multiplier": 38795,
          "shift": 14,
          "approx": 2.36785888671875,
          "relative_error": 7.330628495074588e-06
        },
        "value": {
          "input_scale": 0.00390625,
          "rhs_scale": 0.00037490851479475497,
          "output_scale": 0.000344358656581338,
          "in_bits": 16,
          "rhs_bits": 16,
          "out_bits": 16,
          "real_multiplier": 0.004252793876175138,
          "multiplier": 35675,
          "shift": 23,
          "approx": 0.004252791404724121,
          "relative_error": 5.811358577180437e-07
        },
        "o_proj": {
          "input_scale": 0.000344358656581338,
          "rhs_scale": 9.353510769634414e-06,
          "output_scale": 0.000672473646668546,
          "in_bits": 16,
          "rhs_bits": 16,
          "out_bits": 16,
          "real_multiplier": 4.789722867070145e-06,
          "multiplier": 41143,
          "shift": 33,
          "approx": 4.789675585925579e-06,
          "relative_error": 9.871373747027954e-06
        },
        "gate_proj": {
          "input_scale": 0.0003201958315521788,
          "rhs_scale": 1.6970166529334927e-05,
          "output_scale": 0.00044027371453709136,
          "in_bits": 16,
          "rhs_bits": 16,
          "out_bits": 16,
          "real_multiplier": 1.2341814657621524e-05,
          "multiplier": 3313,
          "shift": 28,
          "approx": 1.2341886758804321e-05,
          "relative_error": 5.842024434592773e-06
        },
        "up_proj": {
          "input_scale": 0.0003201958315521788,
          "rhs_scale": 1.3239929338222886e-05,
          "output_scale": 0.0005301359211797461,
          "in_bits": 16,
          "rhs_bits": 16,
          "out_bits": 16,
          "real_multiplier": 7.996760858442147e-06,
          "multiplier": 17173,
          "shift": 31,
          "approx": 7.996801286935806e-06,
          "relative_error": 5.055608686395054e-06
        },
        "down_proj": {
          "input_scale": 0.001123836546674227,
          "rhs_scale": 1.3245388292016976e-05,
          "output_scale": 0.001236832224832264,
          "in_bits": 16,
          "rhs_bits": 16,
          "out_bits": 16,
          "real_multiplier": 1.203530368840313e-05,
          "multiplier": 51691,
          "shift": 32,
          "approx": 1.2035248801112175e-05,
          "relative_error": 4.560523969863515e-06
        }
      }
    }
  },
  "calibration": {
    "chunks": 2048,
    "seq_len": 16,
    "stride": 8,
    "percentile": 99.5,
    "activation_qmax_for_scale_search": 8191.0,
    "data_file": "/root/compiler-optimization/data/tinystories_head.txt",
    "precision_policy": "int16_baseline",
    "sweep_eval_prompts": [
      "there was a little",
      "once upon a time",
      "the little girl",
      "lily was",
      "one day",
      "the boy was",
      "the bird was",
      "the little boy"
    ]
  }
}